<?xml version="1.0" encoding="utf-8"?>
<S100FC:S100_FC_FeatureCatalogue xmlns:S100FC="http://www.iho.int/S100FC" xmlns:S100Base="http://www.iho.int/S100Base" xmlns:S100CI="http://www.iho.int/S100CI" xmlns:xlink="http://www.w3.org/1999/xlink" xmlns:S100FD="http://www.iho.int/S100FD" xmlns:xsi="http://www.w3.org/2001/XMLSchema-instance" xsi:schemaLocation="http://www.iho.int/S100FC S100FC.xsd">
	<S100FC:name>Feature Catalogue for SV51 Pilot Tug Supporting Service</S100FC:name>
	<S100FC:scope>Pilot Tug Supporting Service</S100FC:scope>
    <S100FC:fieldOfApplication>Marine Navigation</S100FC:fieldOfApplication>
    <S100FC:versionNumber>1.2</S100FC:versionNumber>
    <S100FC:versionDate>2017-08-16</S100FC:versionDate>
	<S100FC:producer>
		<S100CI:role>pointOfContact</S100CI:role>
	</S100FC:producer>
	<S100FC:classification>unclassified</S100FC:classification>
	<S100FC:S100_FC_SimpleAttributes>										
		<S100FC:S100_FC_SimpleAttribute>
			<S100FC:name>Pilotage Request No</S100FC:name>
			<S100FC:definition>Pilotage Request No</S100FC:definition>
			<S100FC:code>pilotReqNo</S100FC:code>
			<S100FC:valueType>text</S100FC:valueType>
		</S100FC:S100_FC_SimpleAttribute>
		<S100FC:S100_FC_SimpleAttribute>
			<S100FC:name>Status</S100FC:name>
			<S100FC:definition>Application status</S100FC:definition>
			<S100FC:code>status</S100FC:code>
			<S100FC:valueType>enumeration</S100FC:valueType>
			<S100FC:listedValues>
				<S100FC:listedValue>
					<S100FC:label>Application</S100FC:label>
					<S100FC:definition>Application</S100FC:definition>
					<S100FC:code>1</S100FC:code>
				</S100FC:listedValue>
				<S100FC:listedValue>
					<S100FC:label>Acknowledgment</S100FC:label>
					<S100FC:definition>Acknowledgment</S100FC:definition>
					<S100FC:code>2</S100FC:code>
				</S100FC:listedValue>
				<S100FC:listedValue>
					<S100FC:label>Emergency</S100FC:label>
					<S100FC:definition>Emergency</S100FC:definition>
					<S100FC:code>3</S100FC:code>
				</S100FC:listedValue>
				<S100FC:listedValue>
					<S100FC:label>Cancellation</S100FC:label>
					<S100FC:definition>Cancellation</S100FC:definition>
					<S100FC:code>4</S100FC:code>
				</S100FC:listedValue>
				<S100FC:listedValue>
					<S100FC:label>PilotonBoard</S100FC:label>
					<S100FC:definition>Pilot on Board</S100FC:definition>
					<S100FC:code>5</S100FC:code>
				</S100FC:listedValue>
				<S100FC:listedValue>
					<S100FC:label>Completion</S100FC:label>
					<S100FC:definition>Completion</S100FC:definition>
					<S100FC:code>6</S100FC:code>
				</S100FC:listedValue>
			</S100FC:listedValues>
		</S100FC:S100_FC_SimpleAttribute>
		<S100FC:S100_FC_SimpleAttribute>
			<S100FC:name>Pilot Request Time</S100FC:name>
			<S100FC:definition>Pilot Request Time</S100FC:definition>
			<S100FC:code>pilotReqTime</S100FC:code>
			<S100FC:valueType>dateTime</S100FC:valueType>
		</S100FC:S100_FC_SimpleAttribute>
		<S100FC:S100_FC_SimpleAttribute>
			<S100FC:name>Ship Name</S100FC:name>
			<S100FC:definition>Ship Name</S100FC:definition>
			<S100FC:code>shipName</S100FC:code>
			<S100FC:valueType>text</S100FC:valueType>
		</S100FC:S100_FC_SimpleAttribute>		
		<S100FC:S100_FC_SimpleAttribute>
			<S100FC:name>Call Letter</S100FC:name>
			<S100FC:definition>Call Letter</S100FC:definition>
			<S100FC:code>callLetter</S100FC:code>
			<S100FC:valueType>text</S100FC:valueType>
		</S100FC:S100_FC_SimpleAttribute>		
        <S100FC:S100_FC_SimpleAttribute>
            <S100FC:name>Gross Tonnage</S100FC:name>
            <S100FC:definition>Gross Tonnage</S100FC:definition>
            <S100FC:code>grossTonnage</S100FC:code>
            <S100FC:valueType>real</S100FC:valueType>
        </S100FC:S100_FC_SimpleAttribute> 
        <S100FC:S100_FC_SimpleAttribute>
            <S100FC:name>Length</S100FC:name>
            <S100FC:definition>Ship Length</S100FC:definition>
            <S100FC:code>length</S100FC:code>
            <S100FC:valueType>real</S100FC:valueType>
        </S100FC:S100_FC_SimpleAttribute>  				
        <S100FC:S100_FC_SimpleAttribute>
            <S100FC:name>Draft</S100FC:name>
            <S100FC:definition>Draft</S100FC:definition>
            <S100FC:code>draft</S100FC:code>
            <S100FC:valueType>real</S100FC:valueType>
        </S100FC:S100_FC_SimpleAttribute> 
		<S100FC:S100_FC_SimpleAttribute>
			<S100FC:name>Pilot Name</S100FC:name>
			<S100FC:definition>Pilot Name</S100FC:definition>
			<S100FC:code>pilotName</S100FC:code>
			<S100FC:valueType>text</S100FC:valueType>
		</S100FC:S100_FC_SimpleAttribute>        		
		<S100FC:S100_FC_SimpleAttribute>
			<S100FC:name>From</S100FC:name>
			<S100FC:definition>Pilot service start point</S100FC:definition>
			<S100FC:code>pilotFrom</S100FC:code>
			<S100FC:valueType>text</S100FC:valueType>
		</S100FC:S100_FC_SimpleAttribute>		
		<S100FC:S100_FC_SimpleAttribute>
			<S100FC:name>To</S100FC:name>
			<S100FC:definition>Pilot service end point</S100FC:definition>
			<S100FC:code>pilotTo</S100FC:code>
			<S100FC:valueType>text</S100FC:valueType>
		</S100FC:S100_FC_SimpleAttribute>				
		<S100FC:S100_FC_SimpleAttribute>
			<S100FC:name>Alongside</S100FC:name>
			<S100FC:definition>Direction of ship's berthing</S100FC:definition>
			<S100FC:code>alongside</S100FC:code>
			<S100FC:valueType>enumeration</S100FC:valueType>
			<S100FC:listedValues>
				<S100FC:listedValue>
					<S100FC:label>Unknow</S100FC:label>
					<S100FC:definition>Unknow</S100FC:definition>
					<S100FC:code>1</S100FC:code>
				</S100FC:listedValue>			
				<S100FC:listedValue>
					<S100FC:label>Starboard</S100FC:label>
					<S100FC:definition>Starboard</S100FC:definition>
					<S100FC:code>2</S100FC:code>
				</S100FC:listedValue>
				<S100FC:listedValue>
					<S100FC:label>Portside</S100FC:label>
					<S100FC:definition>Portside</S100FC:definition>
					<S100FC:code>3</S100FC:code>
				</S100FC:listedValue>
				<S100FC:listedValue>
					<S100FC:label>Stern</S100FC:label>
					<S100FC:definition>Stern</S100FC:definition>
					<S100FC:code>4</S100FC:code>
				</S100FC:listedValue>
				<S100FC:listedValue>
					<S100FC:label>Double</S100FC:label>
					<S100FC:definition>Double</S100FC:definition>
					<S100FC:code>5</S100FC:code>
				</S100FC:listedValue>
			</S100FC:listedValues>
		</S100FC:S100_FC_SimpleAttribute>		
		<S100FC:S100_FC_SimpleAttribute>
			<S100FC:name>Agent Name</S100FC:name>
			<S100FC:definition>Agent Name</S100FC:definition>
			<S100FC:code>agentName</S100FC:code>
			<S100FC:valueType>text</S100FC:valueType>
		</S100FC:S100_FC_SimpleAttribute>
		<S100FC:S100_FC_SimpleAttribute>
			<S100FC:name>Line Handling</S100FC:name>
			<S100FC:definition>Line Handling</S100FC:definition>
			<S100FC:code>lineHandling</S100FC:code>
			<S100FC:valueType>text</S100FC:valueType>
		</S100FC:S100_FC_SimpleAttribute>
		<S100FC:S100_FC_SimpleAttribute>
			<S100FC:name>Remark</S100FC:name>
			<S100FC:definition>Remark</S100FC:definition>
			<S100FC:code>remark</S100FC:code>
			<S100FC:valueType>text</S100FC:valueType>
		</S100FC:S100_FC_SimpleAttribute>
		<S100FC:S100_FC_SimpleAttribute>
			<S100FC:name>Tug Name</S100FC:name>
			<S100FC:definition>Tugboat Name</S100FC:definition>
			<S100FC:code>tugName</S100FC:code>
			<S100FC:valueType>text</S100FC:valueType>
		</S100FC:S100_FC_SimpleAttribute>
		<S100FC:S100_FC_SimpleAttribute>
			<S100FC:name>Main Engine HP</S100FC:name>
			<S100FC:definition>Main Engine HP</S100FC:definition>
			<S100FC:code>mainEngHp</S100FC:code>
			<S100FC:valueType>real</S100FC:valueType>
		</S100FC:S100_FC_SimpleAttribute>
		<S100FC:S100_FC_SimpleAttribute>
			<S100FC:name>Pilot Message</S100FC:name>
			<S100FC:definition>Pilot opinion</S100FC:definition>
			<S100FC:code>pltMessage</S100FC:code>
			<S100FC:valueType>text</S100FC:valueType>
		</S100FC:S100_FC_SimpleAttribute>  
	</S100FC:S100_FC_SimpleAttributes>
	
	
	<S100FC:S100_FC_Roles>
        <S100FC:S100_FC_Role>
            <S100FC:name>Use</S100FC:name>
            <S100FC:definition>do something with it in order to achieve a particular result</S100FC:definition>
            <S100FC:code>use</S100FC:code>
        </S100FC:S100_FC_Role>
        <S100FC:S100_FC_Role>
            <S100FC:name>Used By</S100FC:name>
            <S100FC:definition>do something with it in order to achieve a particular result</S100FC:definition>
            <S100FC:code>usedby</S100FC:code>
        </S100FC:S100_FC_Role>
	</S100FC:S100_FC_Roles>

	
	<S100FC:S100_FC_InformationAssociations>
		<S100FC:S100_FC_InformationAssociation isAbstract="false">
			<S100FC:name>Pilot Service Additional Information</S100FC:name>
			<S100FC:definition>Pilot Service Additional Information</S100FC:definition>
			<S100FC:code>pilotServiceAdditionalInformation</S100FC:code>
			<S100FC:role ref="use"/>
			<S100FC:role ref="usedby"/>
		</S100FC:S100_FC_InformationAssociation>
		<S100FC:S100_FC_InformationAssociation>
			<S100FC:name>Arranged Tug Information</S100FC:name>
			<S100FC:definition>Arranged Tug Information</S100FC:definition>
			<S100FC:code>arrangedTugInformation</S100FC:code>
			<S100FC:role ref="use"/>
			<S100FC:role ref="usedby"/>
		</S100FC:S100_FC_InformationAssociation>
	</S100FC:S100_FC_InformationAssociations>
	
	
	<S100FC:S100_FC_InformationTypes>
		<S100FC:S100_FC_InformationType isAbstract="false">
			<S100FC:name>Pilot Schedule</S100FC:name>
			<S100FC:definition>Pilot Schedule</S100FC:definition>
			<S100FC:code>PilotSchedule</S100FC:code>			
			<S100FC:attributeBinding sequential="false">
				<S100FC:multiplicity>
					<S100Base:lower>1</S100Base:lower>
					<S100Base:upper xsi:nil="false" infinite="false">1</S100Base:upper>
				</S100FC:multiplicity>
				<S100FC:attribute ref="pilotReqNo"/>
			</S100FC:attributeBinding>
			<S100FC:attributeBinding sequential="false">
				<S100FC:multiplicity>
					<S100Base:lower>1</S100Base:lower>
					<S100Base:upper xsi:nil="false" infinite="false">1</S100Base:upper>
				</S100FC:multiplicity>
				<S100FC:permittedValues>
					<S100FC:value>1</S100FC:value>
					<S100FC:value>2</S100FC:value>
					<S100FC:value>3</S100FC:value>
					<S100FC:value>4</S100FC:value>
					<S100FC:value>5</S100FC:value>
					<S100FC:value>6</S100FC:value>
				</S100FC:permittedValues>
				<S100FC:attribute ref="status"/>
			</S100FC:attributeBinding>			
			<S100FC:attributeBinding sequential="false">
				<S100FC:multiplicity>
					<S100Base:lower>1</S100Base:lower>
					<S100Base:upper xsi:nil="false" infinite="false">1</S100Base:upper>
				</S100FC:multiplicity>
				<S100FC:attribute ref="pilotReqTime"/>
			</S100FC:attributeBinding>	
			<S100FC:attributeBinding sequential="false">
				<S100FC:multiplicity>
					<S100Base:lower>1</S100Base:lower>
					<S100Base:upper xsi:nil="false" infinite="false">1</S100Base:upper>
				</S100FC:multiplicity>
				<S100FC:attribute ref="shipName"/>
			</S100FC:attributeBinding>				
			<S100FC:attributeBinding sequential="false">
				<S100FC:multiplicity>
					<S100Base:lower>0</S100Base:lower>
					<S100Base:upper xsi:nil="false" infinite="false">1</S100Base:upper>
				</S100FC:multiplicity>
				<S100FC:attribute ref="callLetter"/>
			</S100FC:attributeBinding>				
			<S100FC:attributeBinding sequential="false">
				<S100FC:multiplicity>
					<S100Base:lower>0</S100Base:lower>
					<S100Base:upper xsi:nil="false" infinite="false">1</S100Base:upper>
				</S100FC:multiplicity>
				<S100FC:attribute ref="grossTonnage"/>
			</S100FC:attributeBinding>				
			<S100FC:attributeBinding sequential="false">
				<S100FC:multiplicity>
					<S100Base:lower>0</S100Base:lower>
					<S100Base:upper xsi:nil="false" infinite="false">1</S100Base:upper>
				</S100FC:multiplicity>
				<S100FC:attribute ref="length"/>
			</S100FC:attributeBinding>				
			<S100FC:attributeBinding sequential="false">
				<S100FC:multiplicity>
					<S100Base:lower>0</S100Base:lower>
					<S100Base:upper xsi:nil="false" infinite="false">1</S100Base:upper>
				</S100FC:multiplicity>
				<S100FC:attribute ref="draft"/>
			</S100FC:attributeBinding>							
			<S100FC:attributeBinding sequential="false">
				<S100FC:multiplicity>
					<S100Base:lower>1</S100Base:lower>
					<S100Base:upper xsi:nil="true" infinite="true"/>
				</S100FC:multiplicity>
				<S100FC:attribute ref="pilotName"/>
			</S100FC:attributeBinding>								
			<S100FC:attributeBinding sequential="false">
				<S100FC:multiplicity>
					<S100Base:lower>1</S100Base:lower>
					<S100Base:upper xsi:nil="false" infinite="false">1</S100Base:upper>
				</S100FC:multiplicity>
				<S100FC:attribute ref="pilotFrom"/>
			</S100FC:attributeBinding>			
			<S100FC:attributeBinding sequential="false">
				<S100FC:multiplicity>
					<S100Base:lower>1</S100Base:lower>
					<S100Base:upper xsi:nil="false" infinite="false">1</S100Base:upper>
				</S100FC:multiplicity>
				<S100FC:attribute ref="pilotTo"/>
			</S100FC:attributeBinding>
			<S100FC:attributeBinding sequential="false">
				<S100FC:multiplicity>
					<S100Base:lower>1</S100Base:lower>
					<S100Base:upper xsi:nil="false" infinite="false">1</S100Base:upper>
				</S100FC:multiplicity>
				<S100FC:permittedValues>
					<S100FC:value>1</S100FC:value>
					<S100FC:value>2</S100FC:value>
					<S100FC:value>3</S100FC:value>
					<S100FC:value>4</S100FC:value>
					<S100FC:value>5</S100FC:value>					
				</S100FC:permittedValues>
				<S100FC:attribute ref="alongside"/>
			</S100FC:attributeBinding>						
			<S100FC:attributeBinding sequential="false">
				<S100FC:multiplicity>
					<S100Base:lower>0</S100Base:lower>
					<S100Base:upper xsi:nil="false" infinite="false">1</S100Base:upper>
				</S100FC:multiplicity>
				<S100FC:attribute ref="agentName"/>
			</S100FC:attributeBinding>
			<S100FC:attributeBinding sequential="false">
				<S100FC:multiplicity>
					<S100Base:lower>0</S100Base:lower>
					<S100Base:upper xsi:nil="false" infinite="false">1</S100Base:upper>
				</S100FC:multiplicity>
				<S100FC:attribute ref="lineHandling"/>
			</S100FC:attributeBinding>
			<S100FC:attributeBinding sequential="false">
				<S100FC:multiplicity>
					<S100Base:lower>0</S100Base:lower>
					<S100Base:upper xsi:nil="false" infinite="false">1</S100Base:upper>
				</S100FC:multiplicity>
				<S100FC:attribute ref="remark"/>
			</S100FC:attributeBinding>
			<S100FC:informationBinding roleType="aggregation">
				<S100FC:multiplicity>
					<S100Base:lower>1</S100Base:lower>
					<S100Base:upper xsi:nil="false" infinite="false">1</S100Base:upper>
				</S100FC:multiplicity>
				<S100FC:association ref="pilotServiceAdditionalInformation"/>
				<S100FC:role ref="use"/>
				<S100FC:informationType ref="PilotOpinionInformation"/>
			</S100FC:informationBinding>
			<S100FC:informationBinding roleType="aggregation">
				<S100FC:multiplicity>
					<S100Base:lower>1</S100Base:lower>
					<S100Base:upper xsi:nil="false" infinite="false">1</S100Base:upper>
				</S100FC:multiplicity>
				<S100FC:association ref="arrangedTugInformation"/>
				<S100FC:role ref="use"/>
				<S100FC:informationType ref="Tug"/>
			</S100FC:informationBinding>
		</S100FC:S100_FC_InformationType>

		<S100FC:S100_FC_InformationType isAbstract="false">
			<S100FC:name>Pilot Opinion Information</S100FC:name>
			<S100FC:definition>Pilot Opinion Information</S100FC:definition>
			<S100FC:code>PilotOpinionInformation</S100FC:code>
			<S100FC:attributeBinding sequential="false">
				<S100FC:multiplicity>
					<S100Base:lower>1</S100Base:lower>
					<S100Base:upper xsi:nil="false" infinite="false">1</S100Base:upper>
				</S100FC:multiplicity>
				<S100FC:attribute ref="pilotName"/>
			</S100FC:attributeBinding>
			<S100FC:attributeBinding sequential="false">
				<S100FC:multiplicity>
					<S100Base:lower>0</S100Base:lower>
					<S100Base:upper xsi:nil="false" infinite="false">1</S100Base:upper>
				</S100FC:multiplicity>
				<S100FC:attribute ref="pltMessage"/>
			</S100FC:attributeBinding>
			
			<S100FC:informationBinding roleType="aggregation">
				<S100FC:multiplicity>
					<S100Base:lower>0</S100Base:lower>
					<S100Base:upper xsi:nil="true" infinite="true"/>
				</S100FC:multiplicity>
				<S100FC:association ref="pilotServiceAdditionalInformation"/>
				<S100FC:role ref="usedby"/>
				<S100FC:informationType ref="PilotSchedule"/>
			</S100FC:informationBinding>			
		</S100FC:S100_FC_InformationType>

		
		<S100FC:S100_FC_InformationType isAbstract="false">
			<S100FC:name>Tug</S100FC:name>
			<S100FC:definition>Tug</S100FC:definition>
			<S100FC:code>Tug</S100FC:code>
			<S100FC:attributeBinding sequential="false">
				<S100FC:multiplicity>
					<S100Base:lower>1</S100Base:lower>
					<S100Base:upper xsi:nil="false" infinite="false">1</S100Base:upper>
				</S100FC:multiplicity>
				<S100FC:attribute ref="tugName"/>
			</S100FC:attributeBinding>			
			<S100FC:attributeBinding sequential="false">
				<S100FC:multiplicity>
					<S100Base:lower>1</S100Base:lower>
					<S100Base:upper xsi:nil="false" infinite="false">1</S100Base:upper>
				</S100FC:multiplicity>
				<S100FC:attribute ref="mainEngHp"/>
			</S100FC:attributeBinding>
			
			<S100FC:informationBinding roleType="aggregation">
				<S100FC:multiplicity>
					<S100Base:lower>0</S100Base:lower>
					<S100Base:upper xsi:nil="true" infinite="true"/>
				</S100FC:multiplicity>
				<S100FC:association ref="arrangedTugInformation"/>
				<S100FC:role ref="usedby"/>
				<S100FC:informationType ref="PilotSchedule"/>
			</S100FC:informationBinding>			
		</S100FC:S100_FC_InformationType>
		
	</S100FC:S100_FC_InformationTypes>
</S100FC:S100_FC_FeatureCatalogue>
